{
  "name": "iTunes (Missing)",
  "includeCustomFormatWhenRenaming": true,
  "specifications": [
    {
      "name": "WEBRIP",
      "implementation": "SourceSpecification",
      "implementationName": "Source",
      "infoLink": "https://wiki.servarr.com/radarr/settings#custom-formats-2",
      "negate": true,
      "required": true,
      "fields": [
        {
          "order": 0,
          "name": "value",
          "label": "Source",
          "value": 8,
          "type": "select",
          "advanced": false,
          "selectOptions": [
            {
              "value": 0,
              "name": "UNKNOWN",
              "order": 0,
              "dividerAfter": false
            },
            {
              "value": 1,
              "name": "CAM",
              "order": 1,
              "dividerAfter": false
            },
            {
              "value": 2,
              "name": "TELESYNC",
              "order": 2,
              "dividerAfter": false
            },
            {
              "value": 3,
              "name": "TELECINE",
              "order": 3,
              "dividerAfter": false
            },
            {
              "value": 4,
              "name": "WORKPRINT",
              "order": 4,
              "dividerAfter": false
            },
            {
              "value": 5,
              "name": "DVD",
              "order": 5,
              "dividerAfter": false
            },
            {
              "value": 6,
              "name": "TV",
              "order": 6,
              "dividerAfter": false
            },
            {
              "value": 7,
              "name": "WEBDL",
              "order": 7,
              "dividerAfter": false
            },
            {
              "value": 8,
              "name": "WEBRIP",
              "order": 8,
              "dividerAfter": false
            },
            {
              "value": 9,
              "name": "BLURAY",
              "order": 9,
              "dividerAfter": false
            }
          ],
          "privacy": "normal",
          "isFloat": false
        }
      ]
    },
    {
      "name": "Amazon Prime: Amazon",
      "implementation": "ReleaseTitleSpecification",
      "implementationName": "Release Title",
      "infoLink": "https://wiki.servarr.com/radarr/settings#custom-formats-2",
      "negate": true,
      "required": true,
      "fields": [
        {
          "order": 0,
          "name": "value",
          "label": "Regular Expression",
          "helpText": "Custom Format RegEx is Case Insensitive",
          "value": "\\b(amzn|amazon)\\b",
          "type": "textbox",
          "advanced": false,
          "privacy": "normal",
          "isFloat": false
        }
      ]
    },
    {
      "name": "Movies Anywhere: Movies Anywhere",
      "implementation": "ReleaseTitleSpecification",
      "implementationName": "Release Title",
      "infoLink": "https://wiki.servarr.com/radarr/settings#custom-formats-2",
      "negate": true,
      "required": true,
      "fields": [
        {
          "order": 0,
          "name": "value",
          "label": "Regular Expression",
          "helpText": "Custom Format RegEx is Case Insensitive",
          "value": "(?<!dts[ .-]?hd[ .-]?)ma\\b(?=.*\\bweb[ ._-]?(dl|rip)\\b)",
          "type": "textbox",
          "advanced": false,
          "privacy": "normal",
          "isFloat": false
        }
      ]
    },
    {
      "name": "Apple TV+: Apple TV+",
      "implementation": "ReleaseTitleSpecification",
      "implementationName": "Release Title",
      "infoLink": "https://wiki.servarr.com/radarr/settings#custom-formats-2",
      "negate": true,
      "required": true,
      "fields": [
        {
          "order": 0,
          "name": "value",
          "label": "Regular Expression",
          "helpText": "Custom Format RegEx is Case Insensitive",
          "value": "\\b(atvp|aptv|Apple TV\\+)\\b",
          "type": "textbox",
          "advanced": false,
          "privacy": "normal",
          "isFloat": false
        }
      ]
    },
    {
      "name": "Disney+: Disney+",
      "implementation": "ReleaseTitleSpecification",
      "implementationName": "Release Title",
      "infoLink": "https://wiki.servarr.com/radarr/settings#custom-formats-2",
      "negate": true,
      "required": true,
      "fields": [
        {
          "order": 0,
          "name": "value",
          "label": "Regular Expression",
          "helpText": "Custom Format RegEx is Case Insensitive",
          "value": "\\b(dsnp|dsny|disney|Disney\\+)\\b",
          "type": "textbox",
          "advanced": false,
          "privacy": "normal",
          "isFloat": false
        }
      ]
    },
    {
      "name": "HBO Max: HBO Max",
      "implementation": "ReleaseTitleSpecification",
      "implementationName": "Release Title",
      "infoLink": "https://wiki.servarr.com/radarr/settings#custom-formats-2",
      "negate": true,
      "required": true,
      "fields": [
        {
          "order": 0,
          "name": "value",
          "label": "Regular Expression",
          "helpText": "Custom Format RegEx is Case Insensitive",
          "value": "\\b(hmax|hbom|hbo[ ._-]max)\\b(?=[ ._-]web[ ._-]?(dl|rip)\\b)",
          "type": "textbox",
          "advanced": false,
          "privacy": "normal",
          "isFloat": false
        }
      ]
    },
    {
      "name": "Netflix: Netflix",
      "implementation": "ReleaseTitleSpecification",
      "implementationName": "Release Title",
      "infoLink": "https://wiki.servarr.com/radarr/settings#custom-formats-2",
      "negate": true,
      "required": true,
      "fields": [
        {
          "order": 0,
          "name": "value",
          "label": "Regular Expression",
          "helpText": "Custom Format RegEx is Case Insensitive",
          "value": "\\b(nf|netflix)\\b",
          "type": "textbox",
          "advanced": false,
          "privacy": "normal",
          "isFloat": false
        }
      ]
    },
    {
      "name": "Peacock TV: Peacock TV",
      "implementation": "ReleaseTitleSpecification",
      "implementationName": "Release Title",
      "infoLink": "https://wiki.servarr.com/radarr/settings#custom-formats-2",
      "negate": true,
      "required": true,
      "fields": [
        {
          "order": 0,
          "name": "value",
          "label": "Regular Expression",
          "helpText": "Custom Format RegEx is Case Insensitive",
          "value": "\\b(pcok|peacock)\\b",
          "type": "textbox",
          "advanced": false,
          "privacy": "normal",
          "isFloat": false
        }
      ]
    },
    {
      "name": "Paramount+: Paramount+",
      "implementation": "ReleaseTitleSpecification",
      "implementationName": "Release Title",
      "infoLink": "https://wiki.servarr.com/radarr/settings#custom-formats-2",
      "negate": true,
      "required": true,
      "fields": [
        {
          "order": 0,
          "name": "value",
          "label": "Regular Expression",
          "helpText": "Custom Format RegEx is Case Insensitive",
          "value": "\\b(pmtp|Paramount Plus)\\b",
          "type": "textbox",
          "advanced": false,
          "privacy": "normal",
          "isFloat": false
        }
      ]
    },
    {
      "name": "WEBDL",
      "implementation": "SourceSpecification",
      "implementationName": "Source",
      "infoLink": "https://wiki.servarr.com/radarr/settings#custom-formats-2",
      "negate": false,
      "required": true,
      "fields": [
        {
          "order": 0,
          "name": "value",
          "label": "Source",
          "value": 7,
          "type": "select",
          "advanced": false,
          "selectOptions": [
            {
              "value": 0,
              "name": "UNKNOWN",
              "order": 0,
              "dividerAfter": false
            },
            {
              "value": 1,
              "name": "CAM",
              "order": 1,
              "dividerAfter": false
            },
            {
              "value": 2,
              "name": "TELESYNC",
              "order": 2,
              "dividerAfter": false
            },
            {
              "value": 3,
              "name": "TELECINE",
              "order": 3,
              "dividerAfter": false
            },
            {
              "value": 4,
              "name": "WORKPRINT",
              "order": 4,
              "dividerAfter": false
            },
            {
              "value": 5,
              "name": "DVD",
              "order": 5,
              "dividerAfter": false
            },
            {
              "value": 6,
              "name": "TV",
              "order": 6,
              "dividerAfter": false
            },
            {
              "value": 7,
              "name": "WEBDL",
              "order": 7,
              "dividerAfter": false
            },
            {
              "value": 8,
              "name": "WEBRIP",
              "order": 8,
              "dividerAfter": false
            },
            {
              "value": 9,
              "name": "BLURAY",
              "order": 9,
              "dividerAfter": false
            }
          ],
          "privacy": "normal",
          "isFloat": false
        }
      ]
    },
    {
      "name": "ROKU: ROKU",
      "implementation": "ReleaseTitleSpecification",
      "implementationName": "Release Title",
      "infoLink": "https://wiki.servarr.com/radarr/settings#custom-formats-2",
      "negate": true,
      "required": true,
      "fields": [
        {
          "order": 0,
          "name": "value",
          "label": "Regular Expression",
          "helpText": "Custom Format RegEx is Case Insensitive",
          "value": "\\b(roku)\\b",
          "type": "textbox",
          "advanced": false,
          "privacy": "normal",
          "isFloat": false
        }
      ]
    },
    {
      "name": "IPT ",
      "implementation": "ReleaseGroupSpecification",
      "implementationName": "Release Group",
      "infoLink": "https://wiki.servarr.com/radarr/settings#custom-formats-2",
      "negate": false,
      "required": true,
      "fields": [
        {
          "order": 0,
          "name": "value",
          "label": "Regular Expression",
          "helpText": "Custom Format RegEx is Case Insensitive",
          "value": "(?<=^|[\\s.-])EVO|CMRG\\b",
          "type": "textbox",
          "advanced": false,
          "privacy": "normal",
          "isFloat": false
        }
      ]
    },
    {
      "name": "Hulu: Hulu",
      "implementation": "ReleaseTitleSpecification",
      "implementationName": "Release Title",
      "infoLink": "https://wiki.servarr.com/radarr/settings#custom-formats-2",
      "negate": true,
      "required": true,
      "fields": [
        {
          "order": 0,
          "name": "value",
          "label": "Regular Expression",
          "helpText": "Custom Format RegEx is Case Insensitive",
          "value": "\\b(hulu)\\b",
          "type": "textbox",
          "advanced": false,
          "privacy": "normal",
          "isFloat": false
        }
      ]
    },
    {
      "name": "iTunes",
      "implementation": "ReleaseTitleSpecification",
      "implementationName": "Release Title",
      "infoLink": "https://wiki.servarr.com/radarr/settings#custom-formats-2",
      "negate": true,
      "required": true,
      "fields": [
        {
          "order": 0,
          "name": "value",
          "label": "Regular Expression",
          "helpText": "Custom Format RegEx is Case Insensitive",
          "value": "\\b(it|itunes)\\b(?=[ ._-]web[ ._-]?(dl|rip)\\b)",
          "type": "textbox",
          "advanced": false,
          "privacy": "normal",
          "isFloat": false
        }
      ]
    }
  ]
}
